{"hourly": {"summary": "Partly cloudy starting tonight, continuing until tomorrow morning.", "data": [{"precipProbability": 0.03, "uvIndex": 1, "pressure": 1020.14, "visibility": 10, "cloudCover": 0.24, "apparentTemperature": 82.33, "windBearing": 120, "humidity": 0.65, "precipIntensity": 0.0002, "time": 1512507600, "summary": "Clear", "dewPoint": 67.27, "ozone": 266.82, "temperature": 79.94, "windSpeed": 5.98, "precipType": "rain", "windGust": 11.2, "icon": "clear-day"}, {"precipProbability": 0, "uvIndex": 0, "pressure": 1020.26, "visibility": 10, "cloudCover": 0.21, "apparentTemperature": 79.23, "windBearing": 116, "humidity": 0.68, "precipIntensity": 0, "time": 1512511200, "summary": "Clear", "dewPoint": 67.05, "ozone": 266.32, "temperature": 78.48, "windSpeed": 8.11, "windGust": 11.69, "icon": "clear-day"}, {"precipProbability": 0, "uvIndex": 0, "pressure": 1020.46, "visibility": 10, "cloudCover": 0.14, "apparentTemperature": 77.37, "windBearing": 112, "humidity": 0.72, "precipIntensity": 0, "time": 1512514800, "summary": "Clear", "dewPoint": 66.99, "ozone": 265.79, "temperature": 76.61, "windSpeed": 10.19, "windGust": 12.34, "icon": "clear-night"}, {"precipProbability": 0.01, "uvIndex": 0, "pressure": 1020.6, "visibility": 10, "cloudCover": 0.09, "apparentTemperature": 76.04, "windBearing": 111, "humidity": 0.76, "precipIntensity": 0.0001, "time": 1512518400, "summary": "Clear", "dewPoint": 67.11, "ozone": 265.29, "temperature": 75.25, "windSpeed": 11.18, "precipType": "rain", "windGust": 12.73, "icon": "clear-night"}, {"precipProbability": 0.01, "uvIndex": 0, "pressure": 1020.81, "visibility": 10, "cloudCover": 0.1, "apparentTemperature": 75.58, "windBearing": 112, "humidity": 0.78, "precipIntensity": 0.0001, "time": 1512522000, "summary": "Clear", "dewPoint": 67.41, "ozone": 264.94, "temperature": 74.74, "windSpeed": 11.48, "precipType": "rain", "windGust": 12.85, "icon": "clear-night"}, {"precipProbability": 0.01, "uvIndex": 0, "pressure": 1021.06, "visibility": 10, "cloudCover": 0.15, "apparentTemperature": 75.39, "windBearing": 115, "humidity": 0.8, "precipIntensity": 0.0002, "time": 1512525600, "summary": "Clear", "dewPoint": 67.77, "ozone": 264.7, "temperature": 74.5, "windSpeed": 11.96, "precipType": "rain", "windGust": 13.02, "icon": "clear-night"}, {"precipProbability": 0.01, "uvIndex": 0, "pressure": 1021.14, "visibility": 10, "cloudCover": 0.21, "apparentTemperature": 75.19, "windBearing": 118, "humidity": 0.81, "precipIntensity": 0.0002, "time": 1512529200, "summary": "Clear", "dewPoint": 68.05, "ozone": 264.46, "temperature": 74.26, "windSpeed": 12.25, "precipType": "rain", "windGust": 13.32, "icon": "clear-night"}, {"precipProbability": 0.02, "uvIndex": 0, "pressure": 1020.9, "visibility": 10, "cloudCover": 0.3, "apparentTemperature": 74.81, "windBearing": 122, "humidity": 0.83, "precipIntensity": 0.0004, "time": 1512532800, "summary": "Partly Cloudy", "dewPoint": 68.29, "ozone": 264.21, "temperature": 73.83, "windSpeed": 12.25, "precipType": "rain", "windGust": 13.98, "icon": "partly-cloudy-night"}, {"precipProbability": 0.04, "uvIndex": 0, "pressure": 1020.49, "visibility": 10, "cloudCover": 0.41, "apparentTemperature": 74.34, "windBearing": 127, "humidity": 0.85, "precipIntensity": 0.0015, "time": 1512536400, "summary": "Partly Cloudy", "dewPoint": 68.45, "ozone": 263.88, "temperature": 73.32, "windSpeed": 12.02, "precipType": "rain", "windGust": 14.69, "icon": "partly-cloudy-night"}, {"precipProbability": 0.06, "uvIndex": 0, "pressure": 1020.12, "visibility": 10, "cloudCover": 0.47, "apparentTemperature": 74.31, "windBearing": 131, "humidity": 0.85, "precipIntensity": 0.0025, "time": 1512540000, "summary": "Partly Cloudy", "dewPoint": 68.42, "ozone": 263.6, "temperature": 73.29, "windSpeed": 11.62, "precipType": "rain", "windGust": 14.91, "icon": "partly-cloudy-night"}, {"precipProbability": 0.04, "uvIndex": 0, "pressure": 1019.88, "visibility": 10, "cloudCover": 0.45, "apparentTemperature": 74.22, "windBearing": 136, "humidity": 0.84, "precipIntensity": 0.0016, "time": 1512543600, "summary": "Partly Cloudy", "dewPoint": 68.08, "ozone": 263.12, "temperature": 73.25, "windSpeed": 10.98, "precipType": "rain", "windGust": 14.31, "icon": "partly-cloudy-night"}, {"precipProbability": 0.02, "uvIndex": 0, "pressure": 1019.69, "visibility": 10, "cloudCover": 0.39, "apparentTemperature": 74.04, "windBearing": 139, "humidity": 0.83, "precipIntensity": 0.0005, "time": 1512547200, "summary": "Partly Cloudy", "dewPoint": 67.59, "ozone": 262.62, "temperature": 73.14, "windSpeed": 10.19, "precipType": "rain", "windGust": 13.26, "icon": "partly-cloudy-night"}, {"precipProbability": 0.02, "uvIndex": 0, "pressure": 1019.54, "visibility": 10, "cloudCover": 0.34, "apparentTemperature": 73.59, "windBearing": 143, "humidity": 0.82, "precipIntensity": 0.0006, "time": 1512550800, "summary": "Partly Cloudy", "dewPoint": 67.09, "ozone": 262.23, "temperature": 72.74, "windSpeed": 9.28, "precipType": "rain", "windGust": 11.98, "icon": "partly-cloudy-night"}, {"precipProbability": 0.03, "uvIndex": 0, "pressure": 1019.5, "visibility": 10, "cloudCover": 0.32, "apparentTemperature": 72.95, "windBearing": 147, "humidity": 0.83, "precipIntensity": 0.0008, "time": 1512554400, "summary": "Partly Cloudy", "dewPoint": 66.54, "ozone": 261.96, "temperature": 72.16, "windSpeed": 8.12, "precipType": "rain", "windGust": 10.4, "icon": "partly-cloudy-night"}, {"precipProbability": 0.03, "uvIndex": 0, "pressure": 1019.54, "visibility": 10, "cloudCover": 0.31, "apparentTemperature": 72.39, "windBearing": 153, "humidity": 0.82, "precipIntensity": 0.0012, "time": 1512558000, "summary": "Partly Cloudy", "dewPoint": 65.98, "ozone": 261.72, "temperature": 71.65, "windSpeed": 6.82, "precipType": "rain", "windGust": 8.67, "icon": "partly-cloudy-night"}, {"precipProbability": 0.04, "uvIndex": 0, "pressure": 1019.69, "visibility": 10, "cloudCover": 0.29, "apparentTemperature": 72.39, "windBearing": 156, "humidity": 0.82, "precipIntensity": 0.0015, "time": 1512561600, "summary": "Partly Cloudy", "dewPoint": 65.72, "ozone": 261.71, "temperature": 71.69, "windSpeed": 6, "precipType": "rain", "windGust": 7.49, "icon": "partly-cloudy-day"}, {"precipProbability": 0.05, "uvIndex": 1, "pressure": 1020.08, "visibility": 10, "cloudCover": 0.28, "apparentTemperature": 74.04, "windBearing": 156, "humidity": 0.78, "precipIntensity": 0.0018, "time": 1512565200, "summary": "Partly Cloudy", "dewPoint": 65.97, "ozone": 261.94, "temperature": 73.35, "windSpeed": 5.96, "precipType": "rain", "windGust": 7.23, "icon": "partly-cloudy-day"}, {"precipProbability": 0.06, "uvIndex": 1, "pressure": 1020.54, "visibility": 10, "cloudCover": 0.26, "apparentTemperature": 77.3, "windBearing": 150, "humidity": 0.71, "precipIntensity": 0.002, "time": 1512568800, "summary": "Partly Cloudy", "dewPoint": 66.45, "ozone": 262.31, "temperature": 76.6, "windSpeed": 6.4, "precipType": "rain", "windGust": 7.54, "icon": "partly-cloudy-day"}, {"precipProbability": 0.06, "uvIndex": 2, "pressure": 1020.69, "visibility": 10, "cloudCover": 0.23, "apparentTemperature": 81.71, "windBearing": 149, "humidity": 0.65, "precipIntensity": 0.0019, "time": 1512572400, "summary": "Clear", "dewPoint": 66.86, "ozone": 262.59, "temperature": 79.49, "windSpeed": 6.93, "precipType": "rain", "windGust": 8.05, "icon": "clear-day"}, {"precipProbability": 0.04, "uvIndex": 3, "pressure": 1020.2, "visibility": 10, "cloudCover": 0.2, "apparentTemperature": 83.79, "windBearing": 145, "humidity": 0.62, "precipIntensity": 0.0011, "time": 1512576000, "summary": "Clear", "dewPoint": 67.02, "ozone": 262.94, "temperature": 81.31, "windSpeed": 7.81, "precipType": "rain", "windGust": 8.75, "icon": "clear-day"}, {"precipProbability": 0.02, "uvIndex": 4, "pressure": 1019.36, "visibility": 10, "cloudCover": 0.15, "apparentTemperature": 84.79, "windBearing": 140, "humidity": 0.6, "precipIntensity": 0.0004, "time": 1512579600, "summary": "Clear", "dewPoint": 67.13, "ozone": 263.21, "temperature": 82.18, "windSpeed": 8.91, "precipType": "rain", "windGust": 9.57, "icon": "clear-day"}, {"precipProbability": 0.02, "uvIndex": 4, "pressure": 1018.58, "visibility": 10, "cloudCover": 0.11, "apparentTemperature": 84.91, "windBearing": 137, "humidity": 0.6, "precipIntensity": 0.0002, "time": 1512583200, "summary": "Clear", "dewPoint": 67.21, "ozone": 263.2, "temperature": 82.27, "windSpeed": 9.66, "precipType": "rain", "windGust": 10.11, "icon": "clear-day"}, {"precipProbability": 0.01, "uvIndex": 3, "pressure": 1017.94, "visibility": 10, "cloudCover": 0.07, "apparentTemperature": 84.16, "windBearing": 136, "humidity": 0.62, "precipIntensity": 0.0002, "time": 1512586800, "summary": "Clear", "dewPoint": 67.22, "ozone": 262.69, "temperature": 81.58, "windSpeed": 9.74, "precipType": "rain", "windGust": 10.08, "icon": "clear-day"}, {"precipProbability": 0.02, "uvIndex": 2, "pressure": 1017.36, "visibility": 10, "cloudCover": 0.03, "apparentTemperature": 83.3, "windBearing": 136, "humidity": 0.63, "precipIntensity": 0.0001, "time": 1512590400, "summary": "Clear", "dewPoint": 67.23, "ozone": 261.91, "temperature": 80.8, "windSpeed": 9.49, "precipType": "rain", "windGust": 9.78, "icon": "clear-day"}, {"precipProbability": 0.01, "uvIndex": 1, "pressure": 1017.05, "visibility": 10, "cloudCover": 0.01, "apparentTemperature": 82.62, "windBearing": 136, "humidity": 0.65, "precipIntensity": 0.0001, "time": 1512594000, "summary": "Clear", "dewPoint": 67.31, "ozone": 261.27, "temperature": 80.19, "windSpeed": 9.26, "precipType": "rain", "windGust": 9.67, "icon": "clear-day"}, {"precipProbability": 0.01, "uvIndex": 0, "pressure": 1017.18, "visibility": 10, "cloudCover": 0.04, "apparentTemperature": 79.54, "windBearing": 137, "humidity": 0.69, "precipIntensity": 0.0002, "time": 1512597600, "summary": "Clear", "dewPoint": 67.56, "ozone": 261.02, "temperature": 78.73, "windSpeed": 9.24, "precipType": "rain", "windGust": 10.21, "icon": "clear-day"}, {"precipProbability": 0.02, "uvIndex": 0, "pressure": 1017.59, "visibility": 10, "cloudCover": 0.09, "apparentTemperature": 77.83, "windBearing": 137, "humidity": 0.74, "precipIntensity": 0.0002, "time": 1512601200, "summary": "Clear", "dewPoint": 67.93, "ozone": 260.89, "temperature": 76.97, "windSpeed": 9.24, "precipType": "rain", "windGust": 11.06, "icon": "clear-night"}, {"precipProbability": 0.02, "uvIndex": 0, "pressure": 1017.95, "visibility": 10, "cloudCover": 0.12, "apparentTemperature": 76.58, "windBearing": 138, "humidity": 0.78, "precipIntensity": 0.0003, "time": 1512604800, "summary": "Clear", "dewPoint": 68.29, "ozone": 260.76, "temperature": 75.65, "windSpeed": 9.16, "precipType": "rain", "windGust": 11.45, "icon": "clear-night"}, {"precipProbability": 0.01, "uvIndex": 0, "pressure": 1018.21, "visibility": 10, "cloudCover": 0.1, "apparentTemperature": 75.88, "windBearing": 138, "humidity": 0.81, "precipIntensity": 0.0002, "time": 1512608400, "summary": "Clear", "dewPoint": 68.61, "ozone": 260.54, "temperature": 74.89, "windSpeed": 8.9, "precipType": "rain", "windGust": 10.82, "icon": "clear-night"}, {"precipProbability": 0.02, "uvIndex": 0, "pressure": 1018.41, "visibility": 10, "cloudCover": 0.06, "apparentTemperature": 75.52, "windBearing": 138, "humidity": 0.83, "precipIntensity": 0.0002, "time": 1512612000, "summary": "Clear", "dewPoint": 68.93, "ozone": 260.52, "temperature": 74.48, "windSpeed": 8.56, "precipType": "rain", "windGust": 9.7, "icon": "clear-night"}, {"precipProbability": 0.02, "uvIndex": 0, "pressure": 1018.6, "visibility": 10, "cloudCover": 0.17, "apparentTemperature": 75.25, "windBearing": 143, "humidity": 0.86, "precipIntensity": 0.0003, "time": 1512615600, "summary": "Clear", "dewPoint": 69.53, "ozone": 260.26, "temperature": 74.12, "windSpeed": 8.68, "precipType": "rain", "windGust": 9.72, "icon": "clear-night"}, {"precipProbability": 0.02, "uvIndex": 0, "pressure": 1018.37, "visibility": 10, "cloudCover": 0.13, "apparentTemperature": 74.76, "windBearing": 144, "humidity": 0.88, "precipIntensity": 0.0004, "time": 1512619200, "summary": "Clear", "dewPoint": 69.65, "ozone": 260.12, "temperature": 73.59, "windSpeed": 8.32, "precipType": "rain", "windGust": 9.27, "icon": "clear-night"}, {"precipProbability": 0.02, "uvIndex": 0, "pressure": 1017.96, "visibility": 10, "cloudCover": 0.11, "apparentTemperature": 74.21, "windBearing": 146, "humidity": 0.89, "precipIntensity": 0.0004, "time": 1512622800, "summary": "Clear", "dewPoint": 69.69, "ozone": 259.86, "temperature": 73.01, "windSpeed": 7.9, "precipType": "rain", "windGust": 8.93, "icon": "clear-night"}, {"precipProbability": 0.02, "uvIndex": 0, "pressure": 1017.52, "visibility": 10, "cloudCover": 0.1, "apparentTemperature": 74.11, "windBearing": 149, "humidity": 0.9, "precipIntensity": 0.0004, "time": 1512626400, "summary": "Clear", "dewPoint": 69.67, "ozone": 259.59, "temperature": 72.91, "windSpeed": 7.38, "precipType": "rain", "windGust": 8.56, "icon": "clear-night"}, {"precipProbability": 0.02, "uvIndex": 0, "pressure": 1017.02, "visibility": 10, "cloudCover": 0.12, "apparentTemperature": 74.1, "windBearing": 155, "humidity": 0.89, "precipIntensity": 0.0004, "time": 1512630000, "summary": "Clear", "dewPoint": 69.53, "ozone": 259.32, "temperature": 72.92, "windSpeed": 6.63, "precipType": "rain", "windGust": 7.98, "icon": "clear-night"}, {"precipProbability": 0.04, "uvIndex": 0, "pressure": 1016.49, "visibility": 10, "cloudCover": 0.17, "apparentTemperature": 73.93, "windBearing": 164, "humidity": 0.89, "precipIntensity": 0.0011, "time": 1512633600, "summary": "Clear", "dewPoint": 69.34, "ozone": 259.02, "temperature": 72.77, "windSpeed": 5.72, "precipType": "rain", "windGust": 7.36, "icon": "clear-night"}, {"precipProbability": 0.06, "uvIndex": 0, "pressure": 1016.15, "visibility": 10, "cloudCover": 0.2, "apparentTemperature": 73.62, "windBearing": 163, "humidity": 0.89, "precipIntensity": 0.0023, "time": 1512637200, "summary": "Clear", "dewPoint": 69.17, "ozone": 258.67, "temperature": 72.47, "windSpeed": 4.93, "precipType": "rain", "windGust": 6.74, "icon": "clear-night"}, {"precipProbability": 0.09, "uvIndex": 0, "pressure": 1016.22, "visibility": 10, "cloudCover": 0.21, "apparentTemperature": 73, "windBearing": 136, "humidity": 0.91, "precipIntensity": 0.0038, "time": 1512640800, "summary": "Clear", "dewPoint": 69.08, "ozone": 258.62, "temperature": 71.84, "windSpeed": 4.29, "precipType": "rain", "windGust": 6.06, "icon": "clear-night"}, {"precipProbability": 0.1, "uvIndex": 0, "pressure": 1016.46, "visibility": 10, "cloudCover": 0.2, "apparentTemperature": 72.42, "windBearing": 122, "humidity": 0.93, "precipIntensity": 0.0057, "time": 1512644400, "summary": "Clear", "dewPoint": 69.03, "ozone": 258.52, "temperature": 71.23, "windSpeed": 3.37, "precipType": "rain", "windGust": 5.39, "icon": "clear-night"}, {"precipProbability": 0.11, "uvIndex": 0, "pressure": 1016.74, "visibility": 10, "cloudCover": 0.19, "apparentTemperature": 72.27, "windBearing": 177, "humidity": 0.94, "precipIntensity": 0.0068, "time": 1512648000, "summary": "Clear", "dewPoint": 69.12, "ozone": 258.63, "temperature": 71.06, "windSpeed": 2.91, "precipType": "rain", "windGust": 5.01, "icon": "clear-night"}, {"precipProbability": 0.1, "uvIndex": 1, "pressure": 1016.99, "visibility": 10, "cloudCover": 0.2, "apparentTemperature": 73.67, "windBearing": 160, "humidity": 0.9, "precipIntensity": 0.0054, "time": 1512651600, "summary": "Clear", "dewPoint": 69.47, "ozone": 258.92, "temperature": 72.48, "windSpeed": 2.93, "precipType": "rain", "windGust": 5.03, "icon": "clear-day"}, {"precipProbability": 0.09, "uvIndex": 1, "pressure": 1017.27, "visibility": 10, "cloudCover": 0.2, "apparentTemperature": 76.63, "windBearing": 129, "humidity": 0.83, "precipIntensity": 0.0033, "time": 1512655200, "summary": "Clear", "dewPoint": 69.96, "ozone": 259.4, "temperature": 75.48, "windSpeed": 4.06, "precipType": "rain", "windGust": 5.4, "icon": "clear-day"}, {"precipProbability": 0.08, "uvIndex": 2, "pressure": 1017.26, "visibility": 10, "cloudCover": 0.2, "apparentTemperature": 79.53, "windBearing": 97, "humidity": 0.76, "precipIntensity": 0.0023, "time": 1512658800, "summary": "Clear", "dewPoint": 70.32, "ozone": 259.66, "temperature": 78.41, "windSpeed": 5.36, "precipType": "rain", "windGust": 5.79, "icon": "clear-day"}, {"precipProbability": 0.1, "uvIndex": 3, "pressure": 1016.8, "visibility": 10, "cloudCover": 0.2, "apparentTemperature": 83.7, "windBearing": 93, "humidity": 0.72, "precipIntensity": 0.0028, "time": 1512662400, "summary": "Clear", "dewPoint": 70.43, "ozone": 259.7, "temperature": 80.29, "windSpeed": 5.7, "precipType": "rain", "windGust": 6.08, "icon": "clear-day"}, {"precipProbability": 0.12, "uvIndex": 4, "pressure": 1016.1, "visibility": 10, "cloudCover": 0.19, "apparentTemperature": 85.23, "windBearing": 108, "humidity": 0.69, "precipIntensity": 0.0039, "time": 1512666000, "summary": "Clear", "dewPoint": 70.44, "ozone": 259.57, "temperature": 81.4, "windSpeed": 6.08, "precipType": "rain", "windGust": 6.28, "icon": "clear-day"}, {"precipProbability": 0.13, "uvIndex": 4, "pressure": 1015.36, "visibility": 10, "cloudCover": 0.19, "apparentTemperature": 85.55, "windBearing": 120, "humidity": 0.69, "precipIntensity": 0.0042, "time": 1512669600, "summary": "Clear", "dewPoint": 70.52, "ozone": 259.4, "temperature": 81.61, "windSpeed": 6.46, "precipType": "rain", "windGust": 6.64, "icon": "clear-day"}, {"precipProbability": 0.1, "uvIndex": 3, "pressure": 1014.64, "visibility": 10, "cloudCover": 0.19, "apparentTemperature": 84.96, "windBearing": 120, "humidity": 0.71, "precipIntensity": 0.0025, "time": 1512673200, "summary": "Clear", "dewPoint": 70.71, "ozone": 259, "temperature": 81.11, "windSpeed": 6.98, "precipType": "rain", "windGust": 7.14, "icon": "clear-day"}, {"precipProbability": 0.06, "uvIndex": 2, "pressure": 1013.89, "visibility": 10, "cloudCover": 0.2, "apparentTemperature": 84.12, "windBearing": 114, "humidity": 0.73, "precipIntensity": 0.0011, "time": 1512676800, "summary": "Clear", "dewPoint": 70.97, "ozone": 258.54, "temperature": 80.45, "windSpeed": 7.56, "precipType": "rain", "windGust": 7.88, "icon": "clear-day"}, {"precipProbability": 0.07, "uvIndex": 1, "pressure": 1013.44, "visibility": 10, "cloudCover": 0.21, "apparentTemperature": 83.33, "windBearing": 108, "humidity": 0.75, "precipIntensity": 0.0014, "time": 1512680400, "summary": "Clear", "dewPoint": 71.2, "ozone": 258.01, "temperature": 79.87, "windSpeed": 8.04, "precipType": "rain", "windGust": 8.64, "icon": "clear-day"}], "icon": "partly-cloudy-night"}, "offset": -5, "minutely": {"summary": "Clear for the hour.", "data": [{"precipProbability": 0, "precipIntensity": 0, "time": 1512508980}, {"precipProbability": 0, "precipIntensity": 0, "time": 1512509040}, {"precipProbability": 0, "precipIntensity": 0, "time": 1512509100}, {"precipProbability": 0, "precipIntensity": 0, "time": 1512509160}, {"precipProbability": 0, "precipIntensity": 0, "time": 1512509220}, {"precipProbability": 0, "precipIntensity": 0, "time": 1512509280}, {"precipProbability": 0, "precipIntensity": 0, "time": 1512509340}, {"precipProbability": 0, "precipIntensity": 0, "time": 1512509400}, {"precipProbability": 0, "precipIntensity": 0, "time": 1512509460}, {"precipProbability": 0, "precipIntensity": 0, "time": 1512509520}, {"precipProbability": 0, "precipIntensity": 0, "time": 1512509580}, {"precipProbability": 0, "precipIntensity": 0, "time": 1512509640}, {"precipProbability": 0, "precipIntensity": 0, "time": 1512509700}, {"precipProbability": 0, "precipIntensity": 0, "time": 1512509760}, {"precipProbability": 0, "precipIntensity": 0, "time": 1512509820}, {"precipProbability": 0, "precipIntensity": 0, "time": 1512509880}, {"precipProbability": 0, "precipIntensity": 0, "time": 1512509940}, {"precipProbability": 0, "precipIntensity": 0, "time": 1512510000}, {"precipProbability": 0, "precipIntensity": 0, "time": 1512510060}, {"precipProbability": 0, "precipIntensity": 0, "time": 1512510120}, {"precipProbability": 0, "precipIntensity": 0, "time": 1512510180}, {"precipProbability": 0, "precipIntensity": 0, "time": 1512510240}, {"precipProbability": 0, "precipIntensity": 0, "time": 1512510300}, {"precipProbability": 0, "precipIntensity": 0, "time": 1512510360}, {"precipProbability": 0, "precipIntensity": 0, "time": 1512510420}, {"precipProbability": 0, "precipIntensity": 0, "time": 1512510480}, {"precipProbability": 0, "precipIntensity": 0, "time": 1512510540}, {"precipProbability": 0, "precipIntensity": 0, "time": 1512510600}, {"precipProbability": 0, "precipIntensity": 0, "time": 1512510660}, {"precipProbability": 0, "precipIntensity": 0, "time": 1512510720}, {"precipProbability": 0, "precipIntensity": 0, "time": 1512510780}, {"precipProbability": 0, "precipIntensity": 0, "time": 1512510840}, {"precipProbability": 0, "precipIntensity": 0, "time": 1512510900}, {"precipProbability": 0, "precipIntensity": 0, "time": 1512510960}, {"precipProbability": 0, "precipIntensity": 0, "time": 1512511020}, {"precipProbability": 0, "precipIntensity": 0, "time": 1512511080}, {"precipProbability": 0, "precipIntensity": 0, "time": 1512511140}, {"precipProbability": 0, "precipIntensity": 0, "time": 1512511200}, {"precipProbability": 0, "precipIntensity": 0, "time": 1512511260}, {"precipProbability": 0, "precipIntensity": 0, "time": 1512511320}, {"precipProbability": 0, "precipIntensity": 0, "time": 1512511380}, {"precipProbability": 0, "precipIntensity": 0, "time": 1512511440}, {"precipProbability": 0, "precipIntensity": 0, "time": 1512511500}, {"precipProbability": 0, "precipIntensity": 0, "time": 1512511560}, {"precipProbability": 0, "precipIntensity": 0, "time": 1512511620}, {"precipProbability": 0, "precipIntensity": 0, "time": 1512511680}, {"precipProbability": 0, "precipIntensity": 0, "time": 1512511740}, {"precipProbability": 0, "precipIntensity": 0, "time": 1512511800}, {"precipProbability": 0, "precipIntensity": 0, "time": 1512511860}, {"precipProbability": 0, "precipIntensity": 0, "time": 1512511920}, {"precipProbability": 0, "precipIntensity": 0, "time": 1512511980}, {"precipProbability": 0, "precipIntensity": 0, "time": 1512512040}, {"precipProbability": 0, "precipIntensity": 0, "time": 1512512100}, {"precipProbability": 0, "precipIntensity": 0, "time": 1512512160}, {"precipProbability": 0, "precipIntensity": 0, "time": 1512512220}, {"precipProbability": 0, "precipIntensity": 0, "time": 1512512280}, {"precipProbability": 0, "precipIntensity": 0, "time": 1512512340}, {"precipProbability": 0, "precipIntensity": 0, "time": 1512512400}, {"precipProbability": 0, "precipIntensity": 0, "time": 1512512460}, {"precipProbability": 0, "precipIntensity": 0, "time": 1512512520}, {"precipProbability": 0, "precipIntensity": 0, "time": 1512512580}], "icon": "clear-day"}, "flags": {"units": "us", "sources": ["isd", "nearest-precip", "nwspa", "cmc", "gfs", "hrrr", "madis", "nam", "sref", "darksky"], "isd-stations": ["722022-12803", "722025-12849", "722030-12844", "722036-99999", "722037-99999", "722039-12885", "722039-99999", "722049-92805", "722049-99999", "722189-92815", "747830-12849", "749044-99999", "994050-99999", "994170-99999", "998305-99999", "999999-12844"]}, "longitude": -80.033776, "latitude": 26.714913, "currently": {"precipProbability": 0, "uvIndex": 1, "pressure": 1020.19, "visibility": 10, "cloudCover": 0.23, "nearestStormDistance": 27, "apparentTemperature": 81.63, "windBearing": 118, "humidity": 0.66, "precipIntensity": 0, "time": 1512509035, "nearestStormBearing": 289, "summary": "Clear", "dewPoint": 67.19, "ozone": 266.62, "temperature": 79.36, "windSpeed": 6.82, "windGust": 11.39, "icon": "clear-day"}, "daily": {"summary": "Rain on Thursday through Saturday, with temperatures peaking at 83\u00b0F on Friday.", "data": [{"precipProbability": 0.35, "uvIndex": 4, "pressure": 1021.16, "apparentTemperatureMin": 73.79, "temperatureMinTime": 1512471600, "precipIntensity": 0.0004, "humidity": 0.73, "apparentTemperatureMaxTime": 1512500400, "sunsetTime": 1512512913, "summary": "Partly cloudy overnight.", "dewPoint": 66.84, "temperatureHighTime": 1512504000, "precipType": "rain", "temperatureMaxTime": 1512504000, "windGust": 13.98, "icon": "partly-cloudy-night", "apparentTemperatureLow": 72.39, "temperatureHigh": 80.41, "temperatureLow": 71.65, "visibility": 10, "ozone": 267.63, "temperatureLowTime": 1512558000, "cloudCover": 0.21, "uvIndexTime": 1512493200, "apparentTemperatureLowTime": 1512561600, "apparentTemperatureMinTime": 1512471600, "windBearing": 118, "precipIntensityMaxTime": 1512471600, "time": 1512450000, "windGustTime": 1512532800, "moonPhase": 0.58, "sunriseTime": 1512474970, "precipIntensityMax": 0.0012, "windSpeed": 6.24, "apparentTemperatureHighTime": 1512500400, "apparentTemperatureMax": 83.03, "temperatureMax": 80.41, "apparentTemperatureHigh": 83.03, "temperatureMin": 73.21}, {"precipProbability": 0.3, "uvIndex": 4, "pressure": 1019.02, "apparentTemperatureMin": 72.39, "temperatureMinTime": 1512558000, "precipIntensity": 0.0008, "humidity": 0.75, "apparentTemperatureMaxTime": 1512583200, "sunsetTime": 1512599320, "summary": "Partly cloudy in the morning.", "dewPoint": 67.53, "temperatureHighTime": 1512583200, "precipType": "rain", "temperatureMaxTime": 1512583200, "windGust": 14.91, "icon": "partly-cloudy-night", "apparentTemperatureLow": 72.27, "temperatureHigh": 82.27, "temperatureLow": 71.06, "visibility": 10, "ozone": 261.96, "temperatureLowTime": 1512648000, "cloudCover": 0.21, "uvIndexTime": 1512579600, "apparentTemperatureLowTime": 1512648000, "apparentTemperatureMinTime": 1512561600, "windBearing": 140, "precipIntensityMaxTime": 1512540000, "time": 1512536400, "windGustTime": 1512540000, "moonPhase": 0.61, "sunriseTime": 1512561412, "precipIntensityMax": 0.0025, "windSpeed": 8.74, "apparentTemperatureHighTime": 1512583200, "apparentTemperatureMax": 84.91, "temperatureMax": 82.27, "apparentTemperatureHigh": 84.91, "temperatureMin": 71.65}, {"precipProbability": 0.49, "uvIndex": 4, "pressure": 1015.7, "apparentTemperatureMin": 72.27, "temperatureMinTime": 1512648000, "precipIntensity": 0.0071, "humidity": 0.84, "apparentTemperatureMaxTime": 1512669600, "sunsetTime": 1512685729, "summary": "Partly cloudy starting in the evening.", "dewPoint": 70.43, "temperatureHighTime": 1512669600, "precipType": "rain", "temperatureMaxTime": 1512669600, "windGust": 14.23, "icon": "partly-cloudy-night", "apparentTemperatureLow": 73.98, "temperatureHigh": 81.61, "temperatureLow": 72.59, "visibility": 10, "ozone": 258.34, "temperatureLowTime": 1512712800, "cloudCover": 0.21, "uvIndexTime": 1512666000, "apparentTemperatureLowTime": 1512712800, "apparentTemperatureMinTime": 1512648000, "windBearing": 127, "precipIntensityMaxTime": 1512702000, "time": 1512622800, "windGustTime": 1512705600, "moonPhase": 0.65, "sunriseTime": 1512647853, "precipIntensityMax": 0.0269, "windSpeed": 6.11, "apparentTemperatureHighTime": 1512669600, "apparentTemperatureMax": 85.55, "temperatureMax": 81.61, "apparentTemperatureHigh": 85.55, "temperatureMin": 71.06}, {"precipProbability": 0.71, "uvIndex": 3, "pressure": 1012.4, "apparentTemperatureMin": 73.98, "temperatureMinTime": 1512712800, "precipIntensity": 0.0259, "humidity": 0.82, "apparentTemperatureMaxTime": 1512756000, "sunsetTime": 1512772140, "summary": "Rain until afternoon, starting again in the evening.", "dewPoint": 70.48, "temperatureHighTime": 1512756000, "precipType": "rain", "temperatureMaxTime": 1512756000, "windGust": 18.87, "icon": "rain", "apparentTemperatureLow": 64.73, "temperatureHigh": 82.9, "temperatureLow": 64.23, "visibility": 10, "ozone": 252.67, "temperatureLowTime": 1512820800, "cloudCover": 0.6, "uvIndexTime": 1512748800, "apparentTemperatureLowTime": 1512820800, "apparentTemperatureMinTime": 1512712800, "windBearing": 199, "precipIntensityMaxTime": 1512745200, "time": 1512709200, "windGustTime": 1512788400, "moonPhase": 0.69, "sunriseTime": 1512734294, "precipIntensityMax": 0.0905, "windSpeed": 10.39, "apparentTemperatureHighTime": 1512756000, "apparentTemperatureMax": 87.23, "temperatureMax": 82.9, "apparentTemperatureHigh": 87.23, "temperatureMin": 72.59}, {"precipProbability": 0.95, "uvIndex": 3, "pressure": 1015.7, "apparentTemperatureMin": 54.09, "temperatureMinTime": 1512878400, "precipIntensity": 0.0588, "humidity": 0.8, "apparentTemperatureMaxTime": 1512795600, "sunsetTime": 1512858552, "summary": "Rain until afternoon and breezy starting in the evening.", "dewPoint": 56.96, "temperatureHighTime": 1512831600, "precipType": "rain", "temperatureMaxTime": 1512795600, "windGust": 28.93, "icon": "rain", "apparentTemperatureLow": 51.26, "temperatureHigh": 66.42, "temperatureLow": 51.26, "ozone": 251.89, "temperatureLowTime": 1512903600, "cloudCover": 0.8, "uvIndexTime": 1512838800, "apparentTemperatureLowTime": 1512903600, "apparentTemperatureMinTime": 1512878400, "windBearing": 304, "precipIntensityMaxTime": 1512831600, "time": 1512795600, "windGustTime": 1512820800, "moonPhase": 0.72, "sunriseTime": 1512820734, "precipIntensityMax": 0.1975, "windSpeed": 13.87, "apparentTemperatureHighTime": 1512831600, "apparentTemperatureMax": 74.24, "temperatureMax": 73.03, "apparentTemperatureHigh": 66.67, "temperatureMin": 54.09}, {"precipProbability": 0, "uvIndex": 5, "pressure": 1022.85, "apparentTemperatureMin": 51.26, "temperatureMinTime": 1512903600, "precipIntensity": 0, "humidity": 0.66, "apparentTemperatureMaxTime": 1512932400, "sunsetTime": 1512944966, "summary": "Breezy in the morning.", "dewPoint": 46.3, "temperatureHighTime": 1512932400, "temperatureMaxTime": 1512932400, "windGust": 24.36, "icon": "wind", "apparentTemperatureLow": 54.75, "temperatureHigh": 65.97, "temperatureLow": 54.75, "ozone": 258.9, "temperatureLowTime": 1512972000, "cloudCover": 0, "uvIndexTime": 1512925200, "apparentTemperatureLowTime": 1512972000, "windBearing": 327, "precipIntensityMaxTime": 1512950400, "time": 1512882000, "windGustTime": 1512896400, "moonPhase": 0.76, "apparentTemperatureHigh": 65.97, "sunriseTime": 1512907174, "temperatureMin": 51.26, "windSpeed": 17.44, "apparentTemperatureHighTime": 1512932400, "apparentTemperatureMax": 65.97, "temperatureMax": 65.97, "precipIntensityMax": 0.0001, "apparentTemperatureMinTime": 1512903600}, {"precipProbability": 0, "uvIndex": 4, "pressure": 1022.69, "apparentTemperatureMin": 54.75, "temperatureMinTime": 1512972000, "precipIntensity": 0, "humidity": 0.68, "apparentTemperatureMaxTime": 1513018800, "sunsetTime": 1513031381, "summary": "Breezy in the morning and partly cloudy starting in the afternoon, continuing until evening.", "dewPoint": 49.85, "temperatureHighTime": 1513018800, "temperatureMaxTime": 1513018800, "windGust": 20.83, "icon": "wind", "apparentTemperatureLow": 50.37, "temperatureHigh": 69.29, "temperatureLow": 50.37, "ozone": 262.02, "temperatureLowTime": 1513076400, "cloudCover": 0.19, "uvIndexTime": 1513008000, "apparentTemperatureLowTime": 1513076400, "windBearing": 337, "precipIntensityMaxTime": 1512993600, "time": 1512968400, "windGustTime": 1512972000, "moonPhase": 0.79, "apparentTemperatureHigh": 69.29, "sunriseTime": 1512993613, "temperatureMin": 54.75, "windSpeed": 13.13, "apparentTemperatureHighTime": 1513018800, "apparentTemperatureMax": 69.29, "temperatureMax": 69.29, "precipIntensityMax": 0.0001, "apparentTemperatureMinTime": 1512972000}, {"precipProbability": 0.03, "uvIndex": 5, "pressure": 1017.15, "apparentTemperatureMin": 50.37, "temperatureMinTime": 1513076400, "precipIntensity": 0.0001, "humidity": 0.67, "apparentTemperatureMaxTime": 1513105200, "sunsetTime": 1513117797, "summary": "Mostly cloudy starting in the afternoon, continuing until evening.", "dewPoint": 49.87, "temperatureHighTime": 1513105200, "precipType": "rain", "temperatureMaxTime": 1513105200, "windGust": 22.47, "icon": "partly-cloudy-day", "apparentTemperatureLow": 56.51, "temperatureHigh": 71.52, "temperatureLow": 56.51, "ozone": 262.82, "temperatureLowTime": 1513166400, "cloudCover": 0.21, "uvIndexTime": 1513098000, "apparentTemperatureLowTime": 1513166400, "apparentTemperatureMinTime": 1513076400, "windBearing": 277, "precipIntensityMaxTime": 1513069200, "time": 1513054800, "windGustTime": 1513137600, "moonPhase": 0.83, "sunriseTime": 1513080051, "precipIntensityMax": 0.0003, "windSpeed": 9.49, "apparentTemperatureHighTime": 1513105200, "apparentTemperatureMax": 71.52, "temperatureMax": 71.52, "apparentTemperatureHigh": 71.52, "temperatureMin": 50.37}], "icon": "rain"}, "timezone": "America/New_York"}